[
  {
    "Summary": "Canarias New Travel",
    "Created": "2022-12-29T11:30:52.000Z",
    "Updated": "2023-06-13T10:37:23.000Z",
    "Status": "In Progress",
    "Due date": "2023-06-15T22:00:00.000Z",
    "Start date": "2023-05-21T22:00:00.000Z",
    "customfield_11517": "[no field found]",
    "customfield_11515": "[no field found]"
  },
  {
    "Summary": "EHTL Viagens",
    "Created": "2023-04-11T08:55:11.000Z",
    "Updated": "2023-06-20T05:02:51.000Z",
    "Status": "In Progress",
    "Due date": "2023-08-03T22:00:00.000Z",
    "Start date": "2023-05-22T22:00:00.000Z",
    "customfield_11517": "[no field found]",
    "customfield_11515": "[no field found]"
  },
  {
    "Summary": "Conextur Argentina",
    "Created": "2023-04-20T15:26:30.000Z",
    "Updated": "2023-06-13T10:39:53.000Z",
    "Resolved": "2023-05-18T05:53:59.000Z",
    "Status": "Completed",
    "Due date": "2023-05-14T22:00:00.000Z",
    "Start date": "2023-02-28T23:00:00.000Z",
    "customfield_11517": "[no field found]",
    "customfield_11515": "[no field found]"
  },
  {
    "Summary": "Allbeds",
    "Created": "2022-12-29T14:22:42.000Z",
    "Updated": "2023-06-13T10:38:47.000Z",
    "Resolved": "2023-05-31T14:31:35.000Z",
    "Status": "Completed",
    "Due date": "2023-05-30T22:00:00.000Z",
    "Start date": "2022-12-28T23:00:00.000Z",
    "customfield_11517": "[no field found]",
    "customfield_11515": "[no field found]"
  },
  {
    "Summary": "Saltour",
    "Created": "2022-12-29T10:27:00.000Z",
    "Updated": "2023-06-19T15:54:34.000Z",
    "Resolved": "2023-05-04T12:49:49.000Z",
    "Status": "Completed",
    "Due date": "2023-05-03T22:00:00.000Z",
    "Start date": "2022-12-28T23:00:00.000Z",
    "customfield_11517": "[no field found]",
    "customfield_11515": "[no field found]"
  },
  {
    "Summary": "Teldar Gekko",
    "Created": "2023-03-07T11:09:45.000Z",
    "Updated": "2023-06-20T05:02:51.000Z",
    "Status": "In Progress",
    "Due date": "2023-07-23T22:00:00.000Z",
    "Start date": "2023-05-31T22:00:00.000Z",
    "customfield_11517": "[no field found]",
    "customfield_11515": "[no field found]"
  },
  {
    "Summary": "RealTime Travel Solutions v2",
    "Created": "2022-04-19T10:34:02.000Z",
    "Updated": "2023-06-15T11:23:32.000Z",
    "Resolved": "2023-05-17T12:57:27.000Z",
    "Status": "Completed",
    "Due date": "2023-05-16T22:00:00.000Z",
    "Start date": "2023-04-18T22:00:00.000Z",
    "customfield_11517": "[no field found]",
    "customfield_11515": "[no field found]"
  },
  {
    "Summary": "CTrip",
    "Created": "2022-12-29T10:57:50.000Z",
    "Updated": "2023-06-19T15:54:42.000Z",
    "Resolved": "2023-05-17T12:55:53.000Z",
    "Status": "Completed",
    "Due date": "2023-05-16T22:00:00.000Z",
    "Start date": "2022-12-28T23:00:00.000Z",
    "customfield_11517": "[no field found]",
    "customfield_11515": "[no field found]"
  },
  {
    "Summary": "TBO Holidays",
    "Created": "2022-12-29T14:33:30.000Z",
    "Updated": "2023-06-19T15:54:38.000Z",
    "Resolved": "2023-05-26T07:30:41.000Z",
    "Status": "Completed",
    "Due date": "2023-05-25T22:00:00.000Z",
    "Start date": "2022-12-28T23:00:00.000Z",
    "customfield_11517": "[no field found]",
    "customfield_11515": "[no field found]"
  },
  {
    "Summary": "Seera Group",
    "Created": "2022-12-29T14:39:03.000Z",
    "Updated": "2023-06-20T05:02:51.000Z",
    "Status": "In Progress",
    "Due date": "2023-06-19T22:00:00.000Z",
    "Start date": "2023-03-22T23:00:00.000Z",
    "customfield_11517": "[no field found]",
    "customfield_11515": "[no field found]"
  },
  {
    "Summary": "The Travel Junction",
    "Created": "2023-05-02T15:13:18.000Z",
    "Updated": "2023-06-19T13:42:24.000Z",
    "Status": "Planned",
    "Due date": "2023-07-17T22:00:00.000Z",
    "Start date": "2023-06-20T22:00:00.000Z",
    "customfield_11517": "[no field found]",
    "customfield_11515": "[no field found]"
  },
  {
    "Summary": "MTS City Breaks",
    "Created": "2023-05-02T14:28:50.000Z",
    "Updated": "2023-06-19T13:42:14.000Z",
    "Status": "Planned",
    "Due date": "2023-07-17T22:00:00.000Z",
    "Start date": "2023-06-20T22:00:00.000Z",
    "customfield_11517": "[no field found]",
    "customfield_11515": "[no field found]"
  },
  {
    "Summary": "NextPax",
    "Created": "2023-05-02T09:23:01.000Z",
    "Updated": "2023-06-19T13:49:57.000Z",
    "Status": "In Progress",
    "Due date": "2023-07-12T22:00:00.000Z",
    "Start date": "2023-06-01T22:00:00.000Z",
    "customfield_11517": "[no field found]",
    "customfield_11515": "[no field found]"
  },
  {
    "Summary": "Booking Agora",
    "Created": "2023-05-02T09:17:59.000Z",
    "Updated": "2023-06-19T14:19:00.000Z",
    "Status": "In Progress",
    "Due date": "2023-07-18T22:00:00.000Z",
    "Start date": "2023-06-07T22:00:00.000Z",
    "customfield_11517": "[no field found]",
    "customfield_11515": "[no field found]"
  },
  {
    "Summary": "Otelz.com",
    "Created": "2023-05-02T06:07:33.000Z",
    "Updated": "2023-06-19T06:07:58.000Z",
    "Status": "ToDo",
    "Due date": "2023-08-21T22:00:00.000Z",
    "Start date": "2023-05-16T22:00:00.000Z",
    "customfield_11517": "[no field found]",
    "customfield_11515": "[no field found]"
  },
  {
    "Summary": "Eurotours",
    "Created": "2023-05-02T06:06:55.000Z",
    "Updated": "2023-06-20T05:02:51.000Z",
    "Status": "In Progress",
    "Due date": "2023-08-22T22:00:00.000Z",
    "Start date": "2023-05-18T22:00:00.000Z",
    "customfield_11517": "[no field found]",
    "customfield_11515": "[no field found]"
  },
  {
    "Summary": "Ezlink",
    "Created": "2023-05-02T06:05:43.000Z",
    "Updated": "2023-06-13T10:42:56.000Z",
    "Status": "Completed",
    "Due date": "2023-06-08T22:00:00.000Z",
    "Start date": "2023-05-14T22:00:00.000Z",
    "customfield_11517": "[no field found]",
    "customfield_11515": "[no field found]"
  },
  {
    "Summary": "Travalco Seller",
    "Created": "2023-05-02T06:03:39.000Z",
    "Updated": "2023-06-14T05:50:43.000Z",
    "Status": "ToDo",
    "Due date": "2023-07-31T22:00:00.000Z",
    "Start date": "2023-06-22T22:00:00.000Z",
    "customfield_11517": "[no field found]",
    "customfield_11515": "[no field found]"
  },
  {
    "Summary": "EverRooms_Seller",
    "Created": "2023-05-02T06:03:02.000Z",
    "Updated": "2023-06-13T10:35:36.000Z",
    "Status": "In Progress",
    "Due date": "2023-06-12T22:00:00.000Z",
    "Start date": "2023-05-16T22:00:00.000Z",
    "customfield_11517": "[no field found]",
    "customfield_11515": "[no field found]"
  },
  {
    "Summary": "Atharva Infotech",
    "Created": "2023-05-02T06:02:21.000Z",
    "Updated": "2023-06-20T05:02:51.000Z",
    "Status": "In Progress",
    "Due date": "2023-07-16T22:00:00.000Z",
    "Start date": "2023-05-31T22:00:00.000Z",
    "customfield_11517": "[no field found]",
    "customfield_11515": "[no field found]"
  },
  {
    "Summary": "DCS Plus",
    "Created": "2023-05-02T06:01:31.000Z",
    "Updated": "2023-06-14T10:13:54.000Z",
    "Status": "ToDo",
    "Due date": "2023-07-05T22:00:00.000Z",
    "Start date": "2023-05-21T22:00:00.000Z",
    "customfield_11517": "[no field found]",
    "customfield_11515": "[no field found]"
  },
  {
    "Summary": "Alpitour (Peakwork)",
    "Created": "2023-05-02T06:00:23.000Z",
    "Updated": "2023-06-19T06:08:06.000Z",
    "Status": "ToDo",
    "Due date": "2023-07-23T22:00:00.000Z",
    "Start date": "2023-05-31T22:00:00.000Z",
    "customfield_11517": "[no field found]",
    "customfield_11515": "[no field found]"
  },
  {
    "Summary": "Travel Compositor",
    "Created": "2023-05-02T05:59:48.000Z",
    "Updated": "2023-06-19T13:48:55.000Z",
    "Status": "In Progress",
    "Due date": "2023-06-26T22:00:00.000Z",
    "Start date": "2023-05-30T22:00:00.000Z",
    "customfield_11517": "[no field found]",
    "customfield_11515": "[no field found]"
  },
  {
    "Summary": "NetSemantics S.A",
    "Created": "2023-05-02T05:57:40.000Z",
    "Updated": "2023-06-14T05:46:30.000Z",
    "Status": "ToDo",
    "Due date": "2023-07-11T22:00:00.000Z",
    "Start date": "2023-06-15T22:00:00.000Z",
    "customfield_11517": "[no field found]",
    "customfield_11515": "[no field found]"
  },
  {
    "Summary": "Sabre",
    "Created": "2023-05-02T05:53:35.000Z",
    "Updated": "2023-06-19T13:54:38.000Z",
    "Status": "In Progress",
    "Due date": "2023-07-25T22:00:00.000Z",
    "Start date": "2023-06-18T22:00:00.000Z",
    "customfield_11517": "[no field found]",
    "customfield_11515": "[no field found]"
  }
]